django_mathfilters-0.4.0.dist-info/DESCRIPTION.rst
django_mathfilters-0.4.0.dist-info/METADATA
django_mathfilters-0.4.0.dist-info/RECORD
django_mathfilters-0.4.0.dist-info/WHEEL
django_mathfilters-0.4.0.dist-info/metadata.json
django_mathfilters-0.4.0.dist-info/top_level.txt
mathfilters/__init__.py
mathfilters/tests.py
mathfilters/templatetags/__init__.py
mathfilters/templatetags/mathfilters.py
